<?xml version="1.0" encoding="utf-8"?><PfoCwPrg Version="3.0"><Number>224</Number><Name>A24SPBGM2698</Name><Date><year>2013</year><month>10</month><day>31</day><hour>16</hour><minute>32</minute></Date><Transformation><ScaleX>1.000</ScaleX><ScaleY>1.000</ScaleY><TransX unit="mm">0.000</TransX><TransY unit="mm">0.000</TransY><Rotation unit="deg">0</Rotation></Transformation><Optic unit="mm">450</Optic><Jumpspeed>4500.000</Jumpspeed><PFODelay>2.000</PFODelay><V_Offset>0.000</V_Offset><D3_active>0</D3_active><shadowwelding>0</shadowwelding><g><point x1="18.320" y1="33.450" z1="0.000" Z="0.000" deFocus="-30.000" PStart="100.000" time="7.000" reruns="1" /><point x1="18.320" y1="29.450" z1="0.000" Z="0.000" deFocus="-30.000" PStart="100.000" time="7.000" reruns="1" /><point x1="22.340" y1="31.730" z1="0.000" Z="0.000" deFocus="-30.000" PStart="100.000" time="7.000" reruns="1" /><point x1="20.230" y1="26.280" z1="0.000" Z="0.000" deFocus="-30.000" PStart="100.000" time="7.000" reruns="1" /><point x1="20.230" y1="20.280" z1="0.000" Z="0.000" deFocus="-30.000" PStart="100.000" time="7.000" reruns="1" /><point x1="20.230" y1="14.280" z1="0.000" Z="0.000" deFocus="-30.000" PStart="100.000" time="7.000" reruns="1" /><point x1="20.230" y1="8.280" z1="0.000" Z="0.000" deFocus="-30.000" PStart="100.000" time="7.000" reruns="1" /><point x1="20.230" y1="2.280" z1="0.000" Z="0.000" deFocus="-30.000" PStart="100.000" time="7.000" reruns="1" /><point x1="20.230" y1="-3.720" z1="0.000" Z="0.000" deFocus="-30.000" PStart="100.000" time="7.000" reruns="1" /><point x1="17.840" y1="-7.670" z1="0.000" Z="0.000" deFocus="-30.000" PStart="100.000" time="7.000" reruns="1" /><point x1="17.720" y1="-11.670" z1="0.000" Z="0.000" deFocus="-30.000" PStart="100.000" time="7.000" reruns="1" /><point x1="22.010" y1="-10.860" z1="0.000" Z="0.000" deFocus="-30.000" PStart="100.000" time="7.000" reruns="1" /><point x1="24.610" y1="-7.360" z1="0.000" Z="0.000" deFocus="-30.000" PStart="100.000" time="7.000" reruns="1" /><point x1="24.690" y1="-2.240" z1="0.000" Z="0.000" deFocus="-30.000" PStart="100.000" time="7.000" reruns="1" /><point x1="24.690" y1="3.760" z1="0.000" Z="0.000" deFocus="-30.000" PStart="100.000" time="7.000" reruns="1" /><point x1="24.690" y1="9.760" z1="0.000" Z="0.000" deFocus="-30.000" PStart="100.000" time="7.000" reruns="1" /><point x1="24.690" y1="15.760" z1="0.000" Z="0.000" deFocus="-30.000" PStart="100.000" time="7.000" reruns="1" /><point x1="24.690" y1="21.760" z1="0.000" Z="0.000" deFocus="-30.000" PStart="100.000" time="7.000" reruns="1" /><point x1="24.690" y1="27.760" z1="0.000" Z="0.000" deFocus="-30.000" PStart="100.000" time="7.000" reruns="1" /></g></PfoCwPrg>