<?xml version="1.0" standalone="no"?><PfoCwPrg Version="3.0"><Number>129</Number><Name>ChevyA WD J5 L13</Name><NoOfPoints>0</NoOfPoints><Transformation><ScaleX>1</ScaleX><ScaleY>1</ScaleY><TransX>0</TransX><TransY>0</TransY><Rotation>0</Rotation></Transformation><Optic unit="mm">450</Optic><Jumpspeed>4500</Jumpspeed><PFODelay>2</PFODelay><V_Offset>0</V_Offset><D3_active>0</D3_active><shadowwelding>0</shadowwelding><ProgType>VectorPower</ProgType><Date><year>2018</year><month>7</month><day>5</day><hour>13</hour><min>43</min><sec>28</sec></Date><g><line x1="-6.114" y1="7.064" z1="0" x2="-6.114" y2="17.004" z2="0" count="2" viewascount="1" ptDistance="9.94" firstpoint="0" Z="0" v="120" deFocusStart="0" deFocus="0" deFocusEnd="0" deFocusStartRampLen="0" deFocusEndRampLen="0" deFocusStartRampAct="0" deFocusEndRampAct="0" PStart="20" PEnd="100" PEndVector="100" PWStart="0" PWEnd="0" PWEndVector="0" RampLen1="1" Ramp1Active="1" RampLen2="0" Ramp2Active="0" reruns="1"></line><circle cx="-3.13" cy="17" cz="0" majx="2.984" majy="0" majz="0" minx="0" miny="2.984" minz="0" r="2.984" phi1="179.92" phi2="89.7" phiOverlap="0" dir="1" count="0" viewascount="1" ptDistance="Infinity" firstpoint="0" Z="0" v="120" deFocusStart="0" deFocus="0" deFocusEnd="0" deFocusStartRampLen="0" deFocusEndRampLen="0" deFocusStartRampAct="0" deFocusEndRampAct="0" PStart="100" PEnd="100" PEndVector="0" PWStart="0" PWEnd="0" PWEndVector="0" RampLen1="0" Ramp1Active="0" RampLen2="0" Ramp2Active="0" reruns="1" /><line x1="-3.114" y1="19.984" z1="0" x2="5.886" y2="19.984" z2="0" count="2" viewascount="1" ptDistance="9" firstpoint="0" Z="0" v="120" deFocusStart="0" deFocus="0" deFocusEnd="0" deFocusStartRampLen="0" deFocusEndRampLen="0" deFocusStartRampAct="0" deFocusEndRampAct="0" PStart="100" PEnd="100" PEndVector="100" PWStart="0" PWEnd="0" PWEndVector="0" RampLen1="0" Ramp1Active="0" RampLen2="0" Ramp2Active="0" reruns="1"></line><circle cx="5.902" cy="17" cz="0" majx="2.984" majy="0" majz="0" minx="0" miny="2.984" minz="0" r="2.984" phi1="90.3" phi2="0.08" phiOverlap="0" dir="1" count="0" viewascount="1" ptDistance="Infinity" firstpoint="0" Z="0" v="120" deFocusStart="0" deFocus="0" deFocusEnd="0" deFocusStartRampLen="0" deFocusEndRampLen="0" deFocusStartRampAct="0" deFocusEndRampAct="0" PStart="100" PEnd="100" PEndVector="0" PWStart="0" PWEnd="0" PWEndVector="0" RampLen1="0" Ramp1Active="0" RampLen2="0" Ramp2Active="0" reruns="1" /><line x1="8.886" y1="17.004" z1="0" x2="8.886" y2="-13.606" z2="0" count="2" viewascount="1" ptDistance="30.61" firstpoint="0" Z="0" v="120" deFocusStart="0" deFocus="0" deFocusEnd="0" deFocusStartRampLen="0" deFocusEndRampLen="0" deFocusStartRampAct="0" deFocusEndRampAct="0" PStart="100" PEnd="100" PEndVector="100" PWStart="0" PWEnd="0" PWEndVector="0" RampLen1="0" Ramp1Active="0" RampLen2="0" Ramp2Active="0" reruns="1"></line><circle cx="5.899" cy="-13.599" cz="0" majx="2.987" majy="0" majz="0" minx="0" miny="2.987" minz="0" r="2.987" phi1="359.86" phi2="269.76" phiOverlap="0" dir="1" count="0" viewascount="1" ptDistance="Infinity" firstpoint="0" Z="0" v="120" deFocusStart="0" deFocus="0" deFocusEnd="0" deFocusStartRampLen="0" deFocusEndRampLen="0" deFocusStartRampAct="0" deFocusEndRampAct="0" PStart="100" PEnd="100" PEndVector="0" PWStart="0" PWEnd="0" PWEndVector="0" RampLen1="0" Ramp1Active="0" RampLen2="0" Ramp2Active="0" reruns="1" /><line x1="5.886" y1="-16.586" z1="0" x2="-8.114" y2="-16.586" z2="0" count="2" viewascount="1" ptDistance="14" firstpoint="0" Z="0" v="120" deFocusStart="0" deFocus="0" deFocusEnd="0" deFocusStartRampLen="0" deFocusEndRampLen="0" deFocusStartRampAct="0" deFocusEndRampAct="0" PStart="100" PEnd="100" PEndVector="100" PWStart="0" PWEnd="0" PWEndVector="0" RampLen1="0" Ramp1Active="0" RampLen2="0" Ramp2Active="0" reruns="1"></line><circle cx="-8.127" cy="-13.599" cz="0" majx="2.987" majy="0" majz="0" minx="0" miny="2.987" minz="0" r="2.987" phi1="270.24" phi2="180.14" phiOverlap="0" dir="1" count="0" viewascount="1" ptDistance="Infinity" firstpoint="0" Z="0" v="120" deFocusStart="0" deFocus="0" deFocusEnd="0" deFocusStartRampLen="0" deFocusEndRampLen="0" deFocusStartRampAct="0" deFocusEndRampAct="0" PStart="100" PEnd="100" PEndVector="0" PWStart="0" PWEnd="0" PWEndVector="0" RampLen1="0" Ramp1Active="0" RampLen2="0" Ramp2Active="0" reruns="1" /><line x1="-11.114" y1="-13.606" z1="0" x2="-11.114" y2="-6.646" z2="0" count="2" viewascount="1" ptDistance="6.96" firstpoint="0" Z="0" v="120" deFocusStart="0" deFocus="0" deFocusEnd="0" deFocusStartRampLen="0" deFocusEndRampLen="0" deFocusStartRampAct="0" deFocusEndRampAct="0" PStart="100" PEnd="100" PEndVector="20" PWStart="0" PWEnd="0" PWEndVector="0" RampLen1="0" Ramp1Active="0" RampLen2="1" Ramp2Active="1" reruns="1"></line></g></PfoCwPrg>