<?xml version="1.0" standalone="no"?><PfoCwPrg Version="4.0"><Number>140</Number><Name>ChevyA WD M4 L31</Name><NoOfPoints>0</NoOfPoints><Transformation><ScaleX>1</ScaleX><ScaleY>1</ScaleY><TransX>0</TransX><TransY>0</TransY><Rotation>0</Rotation></Transformation><Optic unit="mm">450</Optic><Jumpspeed>4500</Jumpspeed><PFODelay>2</PFODelay><V_Offset>0</V_Offset><D3_active>0</D3_active><shadowwelding>0</shadowwelding><ProgType>VectorPower</ProgType><Date><year>2019</year><month>10</month><day>8</day><hour>16</hour><min>56</min><sec>51</sec></Date><g><circle cx="1.916" cy="-15.144" cz="0" majx="3.05" majy="0" majz="0" minx="0" miny="3.05" minz="0" r="3.05" phi1="278.1" phi2="180.7" phiOverlap="0" dir="1" count="0" viewascount="1" ptDistance="Infinity" firstpoint="0" Z="0" v="90" deFocusStart="0" deFocus="0" deFocusEnd="0" deFocusStartRampLen="0" deFocusEndRampLen="0" deFocusStartRampAct="0" deFocusEndRampAct="0" PStart="20" PEnd="100" PEndVector="0" PWStart="0" PWEnd="0" PWEndVector="0" RampLen1="19" Ramp1Active="1" RampLen2="0" Ramp2Active="0" reruns="1" /><line x1="-1.134" y1="-15.184" z1="0" x2="-1.134" y2="8.686" z2="0" count="2" viewascount="1" ptDistance="23.87" firstpoint="0" Z="0" v="90" deFocusStart="0" deFocus="0" deFocusEnd="0" deFocusStartRampLen="0" deFocusEndRampLen="0" deFocusStartRampAct="0" deFocusEndRampAct="0" PStart="100" PEnd="100" PEndVector="100" PWStart="0" PWEnd="0" PWEndVector="0" RampLen1="0" Ramp1Active="0" RampLen2="0" Ramp2Active="0" reruns="1"></line><circle cx="1.871" cy="8.671" cz="0" majx="3.005" majy="0" majz="0" minx="0" miny="3.005" minz="0" r="3.005" phi1="179.72" phi2="90.09" phiOverlap="0" dir="1" count="0" viewascount="1" ptDistance="Infinity" firstpoint="0" Z="0" v="90" deFocusStart="0" deFocus="0" deFocusEnd="0" deFocusStartRampLen="0" deFocusEndRampLen="0" deFocusStartRampAct="0" deFocusEndRampAct="0" PStart="100" PEnd="100" PEndVector="0" PWStart="0" PWEnd="0" PWEndVector="0" RampLen1="0" Ramp1Active="0" RampLen2="0" Ramp2Active="0" reruns="1" /><line x1="1.866" y1="11.676" z1="0" x2="2.346" y2="11.676" z2="0" count="2" viewascount="1" ptDistance="0.48" firstpoint="0" Z="0" v="90" deFocusStart="0" deFocus="0" deFocusEnd="0" deFocusStartRampLen="0" deFocusEndRampLen="0" deFocusStartRampAct="0" deFocusEndRampAct="0" PStart="100" PEnd="100" PEndVector="20" PWStart="0" PWEnd="0" PWEndVector="0" RampLen1="0" Ramp1Active="0" RampLen2="0.48" Ramp2Active="1" reruns="1"></line></g></PfoCwPrg>