<?xml version="1.0" standalone="no"?><PfoCwPrg Version="3.0"><Number>127</Number><Name>ChevyB WD J3 L47</Name><NoOfPoints>0</NoOfPoints><Transformation><ScaleX>1</ScaleX><ScaleY>1</ScaleY><TransX>0</TransX><TransY>0</TransY><Rotation>0</Rotation></Transformation><Optic unit="mm">450</Optic><Jumpspeed>4500</Jumpspeed><PFODelay>2</PFODelay><V_Offset>0</V_Offset><D3_active>0</D3_active><shadowwelding>0</shadowwelding><ProgType>VectorPower</ProgType><Date><year>2018</year><month>7</month><day>6</day><hour>12</hour><min>2</min><sec>49</sec></Date><g><line x1="45.53" y1="30.57" z1="0" x2="42.55" y2="26.58" z2="0" count="2" viewascount="1" ptDistance="4.98" firstpoint="0" Z="0" v="120" deFocusStart="0" deFocus="0" deFocusEnd="0" deFocusStartRampLen="0" deFocusEndRampLen="0" deFocusStartRampAct="0" deFocusEndRampAct="0" PStart="20" PEnd="100" PEndVector="100" PWStart="0" PWEnd="0" PWEndVector="0" RampLen1="1" Ramp1Active="1" RampLen2="0" Ramp2Active="0" reruns="1"></line><circle cx="44.936" cy="24.799" cz="0" majx="2.977" majy="0" majz="0" minx="0" miny="2.977" minz="0" r="2.977" phi1="143.27" phi2="233.38" phiOverlap="0" dir="0" count="0" viewascount="1" ptDistance="Infinity" firstpoint="0" Z="0" v="120" deFocusStart="0" deFocus="0" deFocusEnd="0" deFocusStartRampLen="0" deFocusEndRampLen="0" deFocusStartRampAct="0" deFocusEndRampAct="0" PStart="100" PEnd="100" PEndVector="0" PWStart="0" PWEnd="0" PWEndVector="0" RampLen1="0" Ramp1Active="0" RampLen2="0" Ramp2Active="0" reruns="1" /><line x1="43.16" y1="22.41" z1="0" x2="51.99" y2="15.88" z2="0" count="2" viewascount="1" ptDistance="10.98" firstpoint="0" Z="0" v="120" deFocusStart="0" deFocus="0" deFocusEnd="0" deFocusStartRampLen="0" deFocusEndRampLen="0" deFocusStartRampAct="0" deFocusEndRampAct="0" PStart="100" PEnd="100" PEndVector="100" PWStart="0" PWEnd="0" PWEndVector="0" RampLen1="0" Ramp1Active="0" RampLen2="0" Ramp2Active="0" reruns="1"></line><circle cx="53.775" cy="18.322" cz="0" majx="3.025" majy="0" majz="0" minx="0" miny="3.025" minz="0" r="3.025" phi1="233.84" phi2="322.96" phiOverlap="0" dir="0" count="0" viewascount="1" ptDistance="Infinity" firstpoint="0" Z="0" v="120" deFocusStart="0" deFocus="0" deFocusEnd="0" deFocusStartRampLen="0" deFocusEndRampLen="0" deFocusStartRampAct="0" deFocusEndRampAct="0" PStart="100" PEnd="100" PEndVector="0" PWStart="0" PWEnd="0" PWEndVector="0" RampLen1="0" Ramp1Active="0" RampLen2="0" Ramp2Active="0" reruns="1" /><line x1="56.19" y1="16.5" z1="0" x2="60.66" y2="22.48" z2="0" count="2" viewascount="1" ptDistance="7.47" firstpoint="0" Z="0" v="120" deFocusStart="0" deFocus="0" deFocusEnd="0" deFocusStartRampLen="0" deFocusEndRampLen="0" deFocusStartRampAct="0" deFocusEndRampAct="0" PStart="100" PEnd="100" PEndVector="100" PWStart="0" PWEnd="0" PWEndVector="0" RampLen1="0" Ramp1Active="0" RampLen2="0" Ramp2Active="0" reruns="1"></line><circle cx="58.284" cy="24.258" cz="0" majx="2.967" majy="0" majz="0" minx="0" miny="2.967" minz="0" r="2.967" phi1="323.19" phi2="53.73" phiOverlap="0" dir="0" count="0" viewascount="1" ptDistance="Infinity" firstpoint="0" Z="0" v="120" deFocusStart="0" deFocus="0" deFocusEnd="0" deFocusStartRampLen="0" deFocusEndRampLen="0" deFocusStartRampAct="0" deFocusEndRampAct="0" PStart="100" PEnd="100" PEndVector="0" PWStart="0" PWEnd="0" PWEndVector="0" RampLen1="0" Ramp1Active="0" RampLen2="0" Ramp2Active="0" reruns="1" /><line x1="60.04" y1="26.65" z1="0" x2="46.4" y2="36.73" z2="0" count="2" viewascount="1" ptDistance="16.96" firstpoint="0" Z="0" v="120" deFocusStart="0" deFocus="0" deFocusEnd="0" deFocusStartRampLen="0" deFocusEndRampLen="0" deFocusStartRampAct="0" deFocusEndRampAct="0" PStart="100" PEnd="100" PEndVector="100" PWStart="0" PWEnd="0" PWEndVector="0" RampLen1="0" Ramp1Active="0" RampLen2="0" Ramp2Active="0" reruns="1"></line><circle cx="44.608" cy="34.304" cz="0" majx="3.016" majy="0" majz="0" minx="0" miny="3.016" minz="0" r="3.016" phi1="53.54" phi2="142.98" phiOverlap="0" dir="0" count="0" viewascount="1" ptDistance="Infinity" firstpoint="0" Z="0" v="120" deFocusStart="0" deFocus="0" deFocusEnd="0" deFocusStartRampLen="0" deFocusEndRampLen="0" deFocusStartRampAct="0" deFocusEndRampAct="0" PStart="100" PEnd="100" PEndVector="0" PWStart="0" PWEnd="0" PWEndVector="0" RampLen1="0" Ramp1Active="0" RampLen2="0" Ramp2Active="0" reruns="1" /><line x1="42.2" y1="36.12" z1="0" x2="41.01" y2="34.52" z2="0" count="2" viewascount="1" ptDistance="1.99" firstpoint="0" Z="0" v="120" deFocusStart="0" deFocus="0" deFocusEnd="0" deFocusStartRampLen="0" deFocusEndRampLen="0" deFocusStartRampAct="0" deFocusEndRampAct="0" PStart="100" PEnd="100" PEndVector="20" PWStart="0" PWEnd="0" PWEndVector="0" RampLen1="0" Ramp1Active="0" RampLen2="1" Ramp2Active="1" reruns="1"></line></g></PfoCwPrg>